open_geo_engine/__init__.py
open_geo_engine/__main__.py
open_geo_engine/bootstrap.py
open_geo_engine/config/__init__.py
open_geo_engine/config/model_settings.py
open_geo_engine/src/__init__.py
open_geo_engine/src/bootstrap.py
open_geo_engine/src/generate_building_centroids.py
open_geo_engine/src/get_google_streetview.py
open_geo_engine/src/load_ee_data.py
open_geo_engine/utils/__init__.py
open_geo_engine/utils/utils.py
open_geo_engine-0.1.3.dist-info/LICENSE
open_geo_engine-0.1.3.dist-info/WHEEL
open_geo_engine-0.1.3.dist-info/METADATA
open_geo_engine-0.1.3.dist-info/RECORD
