Metadata-Version: 2.1
Name: open-geo-engine
Version: 0.1.3
Summary: 
Author: ChristinaLast
Author-email: christina.last@outlook.com
Requires-Python: >=3.10,<3.12
Classifier: Programming Language :: Python :: 3
Classifier: Programming Language :: Python :: 3.10
Requires-Dist: click-config-file (>=0.6.0,<0.7.0)
Requires-Dist: click-option-group (>=0.5.3,<0.6.0)
Requires-Dist: earthengine-api (>=0.1.323,<0.2.0)
Requires-Dist: esda (>=2.4.3,<3.0.0)
Requires-Dist: gcloud (>=0.18.3,<0.19.0)
Requires-Dist: geemap (>=0.16.9,<0.17.0)
Requires-Dist: geopandas (>=0.11.1,<0.12.0)
Requires-Dist: google (>=3.0.0,<4.0.0)
Requires-Dist: google-streetview (>=1.2.9,<2.0.0)
Requires-Dist: ipykernel (>=6.15.2,<7.0.0)
Requires-Dist: ipyleaflet (>=0.17.1,<0.18.0)
Requires-Dist: joblib (>=1.1.0,<2.0.0)
Requires-Dist: libpysal (>=4.6.2,<5.0.0)
Requires-Dist: osmnx (>=1.2.2,<2.0.0)
Requires-Dist: scikit-learn (>=1.1.2,<2.0.0)
Requires-Dist: scipy (==1.9.1)
Requires-Dist: setuptools (>=65.3.0,<66.0.0)
